gpsreporter/__init__.py
gpsreporter/__main__.py
gpsreporter/daemon.py
gpsreporter/keys.py
carpi_gpsreporter-0.1.1.dev211212223454.dist-info/LICENSE
carpi_gpsreporter-0.1.1.dev211212223454.dist-info/METADATA
carpi_gpsreporter-0.1.1.dev211212223454.dist-info/WHEEL
carpi_gpsreporter-0.1.1.dev211212223454.dist-info/top_level.txt
carpi_gpsreporter-0.1.1.dev211212223454.dist-info/RECORD
